{"tagline":"whufacemesh.com top 10 girls","body":"whu_top10\r\n=========\r\n### 起初，有了这个网站\r\n[http://whuface.com/](http://whuface.com/)\r\n\r\n### 然后，有了这个project\r\n自动下载[http://whuface.com/](http://whuface.com/)上[TOP 10](http://whuface.com/#top) girls的图片哦，谁没事会比较这些个姑娘们啊，活了30年了，第一次见这么无聊的人。。。\r\n\r\n### Gem require \r\n`nokogiri`\r\n\r\n### Usage\r\n`ruby whu.rb`\r\n\r\n### Screenshot\r\n![whu_top10_screenshot_0720](http://ww4.sinaimg.cn/large/620092a9jw1dv33oo2nf2j.jpg)\r\n![whu_top10_screenshot_0719](http://ww1.sinaimg.cn/large/620092a9jw1dv2d6rb0l8j.jpg)\r\n\r\n### Twitter\r\n[fanweixiao](https://twitter.com/fanweixiao)\r\n\r\n### Weibo\r\n[维生素CC](http://weibo.com/fanweixiao)\r\n\r\n### change log\r\n* v1.0.1\r\n\t* 支持迁移到amazone后的图片服务器\r\n\t* 存储文件名按照mm-dd-hh-mm-sequenceNumber-imageId.jpg格式保存，其中sequenceNumber为当前排名，imageId为该图片的id","google":"","note":"Don't delete this file! It's used internally to help with page regeneration.","name":"Whu top10"}